iiif_downloader
