Metadata-Version: 1.0
Name: iiif-downloader
Version: 0.0.8
Summary: Download images from IIIF servers
Home-page: https://github.com/yaledhlab/iiif-downloader
Author: Douglas Duhaime
Author-email: douglas.duhaime@gmail.com
License: MIT
Keywords: iiif,image-data,api
Platform: UNKNOWN
